supabase/__init__.py
supabase/_async/__init__.py
supabase/_async/auth_client.py
supabase/_async/client.py
supabase/_sync/__init__.py
supabase/_sync/auth_client.py
supabase/_sync/client.py
supabase/client.py
supabase/lib/__init__.py
supabase/lib/client_options.py
supabase/py.typed
supabase/types.py
supabase/version.py
supabase-2.23.1.dist-info/licenses/LICENSE
supabase-2.23.1.dist-info/WHEEL
supabase-2.23.1.dist-info/METADATA
supabase-2.23.1.dist-info/RECORD
